cli.py
grex.py
operators.py
rexactor.py
trex.py
rexactor-1.0.dist-info/LICENSE.txt
rexactor-1.0.dist-info/METADATA
rexactor-1.0.dist-info/WHEEL
rexactor-1.0.dist-info/entry_points.txt
rexactor-1.0.dist-info/top_level.txt
rexactor-1.0.dist-info/RECORD
